TPFinal/Fuentes/crc.vhd
-- ####### CRC-16/USB #######
-- CRC polynomial: 0x8005
-- Input reflected: yes
-- Output reflected: yes
-- Seed value: 0xFFFF
-- XOR-out value: 0xFFFF (IIUC, negate the CRC)

library ieee;
use ieee.std_logic_1164.all;

use ieee.numeric_std.all;

entity crc is
  port (
    clk : in std_logic;
    data_in : in std_logic_vector(7 downto 0);
    crc_en : in std_logic; 
    rst : in std_logic; 
    crc_out : out std_logic_vector(15 downto 0)
  );
end crc;

architecture crc_arch of crc is

  function reverse_vector(v : in std_logic_vector)
    return std_logic_vector is
    variable result : std_logic_vector(v'range);
    alias vr : std_logic_vector(v'REVERSE_RANGE) is v;
  begin
    for i in vr'range loop
      result(i) := vr(i);
    end loop;

    return result;
  end;
  function crc16(data_i : in std_logic_vector(7 downto 0); crc_i : in std_logic_vector(15 downto 0))
    return std_logic_vector is
    variable crc_o : std_logic_vector(15 downto 0);
  begin
    crc_o(15) := crc_i(7) xor crc_i(8) xor crc_i(9) xor crc_i(10) xor crc_i(11) xor crc_i(12) xor crc_i(13) xor crc_i(14) xor crc_i(15) xor data_i(0) xor data_i(1) xor data_i(2) xor data_i(3) xor data_i(4) xor data_i(5) xor data_i(6) xor data_i(7);
    crc_o(14) := crc_i(6);
    crc_o(13) := crc_i(5);
    crc_o(12) := crc_i(4);
    crc_o(11) := crc_i(3);
    crc_o(10) := crc_i(2);
    crc_o(9) := crc_i(1) xor crc_i(15) xor data_i(7);
    crc_o(8) := crc_i(0) xor crc_i(14) xor crc_i(15) xor data_i(6) xor data_i(7);
    crc_o(7) := crc_i(13) xor crc_i(14) xor data_i(5) xor data_i(6);
    crc_o(6) := crc_i(12) xor crc_i(13) xor data_i(4) xor data_i(5);
    crc_o(5) := crc_i(11) xor crc_i(12) xor data_i(3) xor data_i(4);
    crc_o(4) := crc_i(10) xor crc_i(11) xor data_i(2) xor data_i(3);
    crc_o(3) := crc_i(9) xor crc_i(10) xor data_i(1) xor data_i(2);
    crc_o(2) := crc_i(8) xor crc_i(9) xor data_i(0) xor data_i(1);
    crc_o(1) := crc_i(9) xor crc_i(10) xor crc_i(11) xor crc_i(12) xor crc_i(13) xor crc_i(14) xor crc_i(15) xor data_i(1) xor data_i(2) xor data_i(3) xor data_i(4) xor data_i(5) xor data_i(6) xor data_i(7);
    crc_o(0) := crc_i(8) xor crc_i(9) xor crc_i(10) xor crc_i(11) xor crc_i(12) xor crc_i(13) xor crc_i(14) xor crc_i(15) xor data_i(0) xor data_i(1) xor data_i(2) xor data_i(3) xor data_i(4) xor data_i(5) xor data_i(6) xor data_i(7);

    return crc_o;

  end;

  signal crc_o : std_logic_vector (15 downto 0);


begin

  -- crc_out <= not reverse_vector(crc16(reverse_vector(data_in), x"FFFF"));

  process (clk) -- ADDED process
    variable crc_en0 : std_logic := '0';
    variable crc_en1 : std_logic := '0';
  begin
    if rising_edge(clk) then
      if rst = '1' then
        crc_o <= x"FFFF";
        crc_en0 := '0';
        crc_en1 := '0';
      else 
        crc_en1 := crc_en0;
        crc_en0 := crc_en;
        if (not crc_en1 and crc_en0) = '1' then -- detect rising edge of crc_en
          crc_o <= crc16(reverse_vector(data_in), crc_o);
        end if;
      end if;
    end if;
  end process;

  crc_out <= not reverse_vector(crc_o);

end architecture crc_arch;

TPFinal/Fuentes/crc_tb.vhd
library ieee;
use ieee.std_logic_1164.all;
use ieee.numeric_std.all;

entity crc_tb is
end entity;

architecture foo of crc_tb is

  signal data_in : std_logic_vector (7 downto 0);
  signal crc_en : std_logic := '0';
  signal rst : std_logic;
  signal clk : std_logic := '0';
  signal crc_out : std_logic_vector (15 downto 0);

begin

  clk <= not clk after 10 ns;

  DUT :
  entity work.crc
    port map(
      data_in => data_in,
      crc_en => crc_en,
      rst => rst,
      clk => clk,
      crc_out => crc_out
    );

    STIMULI :
    process
    begin
      rst <= '1';
      for i in 0 to 5 loop
        wait until rising_edge(clk);
      end loop;
      rst <= '0';
      
      for i in 1 to 15 loop
        data_in <= std_logic_vector(to_unsigned (i * 10, 8));
        if( i = 2) then
          crc_en <= '1';
        elsif (i = 6) then
          crc_en <= '0';
        elsif (i = 8) then
          rst <= '1';
        elsif (i = 10) then

          crc_en <= '1';
        elsif (i = 11) then
          rst <= '0';
        end if;
        wait until rising_edge(clk);
      end loop;
      crc_en <= '0';
      wait until rising_edge(clk);
      wait;
    end process;
  end architecture;

TPFinal/Simulacion/crc_tb.vcd
$date
  Sat Jun 11 20:14:43 2022
$end
$version
  GHDL v0
$end
$timescale
  1 fs
$end
$scope module standard $end
$upscope $end
$scope module std_logic_1164 $end
$upscope $end
$scope module numeric_std $end
$upscope $end
$scope module crc_tb $end
$var reg 8 ! data_in[7:0] $end
$var reg 1 " crc_en $end
$var reg 1 # rst $end
$var reg 1 $ clk $end
$var reg 16 % crc_out[15:0] $end
$scope module dut $end
$var reg 1 & clk $end
$var reg 8 ' data_in[7:0] $end
$var reg 1 ( crc_en $end
$var reg 1 ) rst $end
$var reg 16 * crc_out[15:0] $end
$var reg 16 + crc_o[15:0] $end
$upscope $end
$upscope $end
$enddefinitions $end
#0
bUUUUUUUU !
0"
1#
0$
bUUUUUUUUUUUUUUUU %
0&
bUUUUUUUU '
0(
1)
bUUUUUUUUUUUUUUUU *
bUUUUUUUUUUUUUUUU +
#10000000
1$
b0000000000000000 %
1&
b0000000000000000 *
b1111111111111111 +
#20000000
0$
0&
#30000000
1$
1&
#40000000
0$
0&
#50000000
1$
1&
#60000000
0$
0&
#70000000
1$
1&
#80000000
0$
0&
#90000000
1$
1&
#100000000
0$
0&
#110000000
b00001010 !
0#
1$
1&
b00001010 '
0)
#120000000
0$
0&
#130000000
b00010100 !
1"
1$
1&
b00010100 '
1(
#140000000
0$
0&
#150000000
b00011110 !
1$
b1011000001000000 %
1&
b00011110 '
b1011000001000000 *
b1111110111110010 +
#160000000
0$
0&
#170000000
b00101000 !
1$
1&
b00101000 '
#180000000
0$
0&
#190000000
b00110010 !
1$
1&
b00110010 '
#200000000
0$
0&
#210000000
b00111100 !
0"
1$
1&
b00111100 '
0(
#220000000
0$
0&
#230000000
b01000110 !
1$
1&
b01000110 '
#240000000
0$
0&
#250000000
b01010000 !
1#
1$
1&
b01010000 '
1)
#260000000
0$
0&
#270000000
b01011010 !
1$
b0000000000000000 %
1&
b01011010 '
b0000000000000000 *
b1111111111111111 +
#280000000
0$
0&
#290000000
b01100100 !
1"
1$
1&
b01100100 '
1(
#300000000
0$
0&
#310000000
b01101110 !
0#
1$
1&
b01101110 '
0)
#320000000
0$
0&
#330000000
b01111000 !
1$
b0101001111000001 %
1&
b01111000 '
b0101001111000001 *
b0111110000110101 +
#340000000
0$
0&
#350000000
b10000010 !
1$
1&
b10000010 '
#360000000
0$
0&
#370000000
b10001100 !
1$
1&
b10001100 '
#380000000
0$
0&
#390000000
b10010110 !
1$
1&
b10010110 '
#400000000
0$
0&
#410000000
0"
1$
1&
0(
